pymenta/Ambiente.py
pymenta/__init__.py
Pymenta-0.1.1.dist-info/LICENSE
Pymenta-0.1.1.dist-info/METADATA
Pymenta-0.1.1.dist-info/WHEEL
Pymenta-0.1.1.dist-info/top_level.txt
Pymenta-0.1.1.dist-info/RECORD
